DatabaseLibrary/__init__.py
DatabaseLibrary/assertion.py
DatabaseLibrary/connection_manager.py
DatabaseLibrary/params_decorator.py
DatabaseLibrary/query.py
DatabaseLibrary/version.py
robotframework_databaselibrary-2.4.0.dist-info/licenses/LICENSE
robotframework_databaselibrary-2.4.0.dist-info/METADATA
robotframework_databaselibrary-2.4.0.dist-info/WHEEL
robotframework_databaselibrary-2.4.0.dist-info/top_level.txt
robotframework_databaselibrary-2.4.0.dist-info/RECORD
