Metadata-Version: 2.4
Name: robotframework-databaselibrary
Version: 2.4.0
Summary: Database Library for Robot Framework
Author-email: Franz Allan Valencia See <franz.see@gmail.com>
License: Apache License 2.0
Project-URL: Homepage, https://github.com/MarketSquare/Robotframework-Database-Library
Project-URL: Keyword docs, http://marketsquare.github.io/Robotframework-Database-Library/
Classifier: Programming Language :: Python :: 3
Classifier: License :: OSI Approved :: Apache Software License
Classifier: Operating System :: OS Independent
Requires-Python: >=3.8.1
License-File: LICENSE
Requires-Dist: robotframework>=5.0.1
Requires-Dist: robotframework-assertion-engine
Requires-Dist: sqlparse
Dynamic: license-file
